mlmongo/__init__.py
mlmongo/asyncs.py
mlmongo/model.py
mlmongo/sync.py
mlmongo/__pycache__/asyncs.cpython-312.pyc
mlmongo/__pycache__/model.cpython-312.pyc
mlmongo-2.0.3.dist-info/METADATA
mlmongo-2.0.3.dist-info/WHEEL
mlmongo-2.0.3.dist-info/top_level.txt
mlmongo-2.0.3.dist-info/RECORD
