Metadata-Version: 2.4
Name: mlmongo
Version: 2.0.3
Summary: mongodb数据库操作工具类
Home-page: https://www.python.org
Author: mengling
Author-email: 1321443305@qq.com
Requires-Python: >=3.8
Requires-Dist: pymongo
Requires-Dist: pydantic
Provides-Extra: all
Requires-Dist: motor; extra == "all"
Dynamic: author
Dynamic: author-email
Dynamic: home-page
Dynamic: provides-extra
Dynamic: requires-dist
Dynamic: requires-python
Dynamic: summary
